atlantis_tools/__init__.py
atlantis_tools/model_upload.py
atlantis_tools/utils.py
atlantis_tools-0.0.3.dist-info/METADATA
atlantis_tools-0.0.3.dist-info/WHEEL
atlantis_tools-0.0.3.dist-info/top_level.txt
atlantis_tools-0.0.3.dist-info/RECORD
